setup.py
tardbm.py
tardbm.egg-info/PKG-INFO
tardbm.egg-info/SOURCES.txt
tardbm.egg-info/dependency_links.txt
tardbm.egg-info/top_level.txt